SuperMiner/SMiner.py
SuperMiner/SNCOM.py
SuperMiner/__init__.py
SuperMiner-22.3.1.2.dist-info/LICENSE
SuperMiner-22.3.1.2.dist-info/METADATA
SuperMiner-22.3.1.2.dist-info/WHEEL
SuperMiner-22.3.1.2.dist-info/entry_points.txt
SuperMiner-22.3.1.2.dist-info/top_level.txt
SuperMiner-22.3.1.2.dist-info/RECORD
