Metadata-Version: 2.1
Name: SuperMiner
Version: 22.3.1.2
Summary: Web miner built based on selenium but more simple operations
Home-page: https://airscker.github.io/SuperWebMiner/
Author: Airscker
License: UNKNOWN
Project-URL: Project, https://github.com/Airscker/SuperWebMiner
Keywords: web,miner,highly composed
Platform: UNKNOWN
Classifier: Development Status :: 5 - Production/Stable
Classifier: Intended Audience :: Developers
Classifier: Topic :: Software Development :: Build Tools
Classifier: Programming Language :: Python :: 3
Classifier: Programming Language :: Python :: 3.7
Classifier: Programming Language :: Python :: 3.8
Classifier: Programming Language :: Python :: 3.9
Classifier: Programming Language :: Python :: 3.10
Classifier: Programming Language :: Python :: 3 :: Only
Requires-Python: >=3.5, <=3.10
License-File: LICENSE
Requires-Dist: requests
Requires-Dist: urllib3
Requires-Dist: selenium
Requires-Dist: lxml
Requires-Dist: bs4
Requires-Dist: click
Requires-Dist: setuptools
